dce_plugin/__init__.py
dce_plugin/docker_client.py
dce_plugin-1.0.dist-info/METADATA
dce_plugin-1.0.dist-info/RECORD
dce_plugin-1.0.dist-info/WHEEL
dce_plugin-1.0.dist-info/top_level.txt
