Metadata-Version: 2.1
Name: dce-plugin
Version: 1.0
Summary: DCE plugin SDK for Python.
Home-page: https://github.com/DaoCloud/dce-plugin-sdk-py
Author: UNKNOWN
Author-email: UNKNOWN
License: UNKNOWN
Platform: UNKNOWN
Classifier: Development Status :: 5 - Production/Stable
Classifier: Environment :: Other Environment
Classifier: Intended Audience :: Developers
Classifier: Operating System :: OS Independent
Classifier: Programming Language :: Python
Classifier: Programming Language :: Python :: 2
Classifier: Programming Language :: Python :: 2.7
Classifier: Topic :: Utilities
